{
  "tournament": {
    "id": "wc2026",
    "name": "FIFA World Cup 2026",
    "host": "Canada, Mexico, United States"
  },
  "teams": [
    {
      "code": "MEX",
      "name": "Mexico",
      "group": "A"
    },
    {
      "code": "CZE",
      "name": "Czechia",
      "group": "A"
    },
    {
      "code": "RSA",
      "name": "South Africa",
      "group": "A"
    },
    {
      "code": "KOR",
      "name": "South Korea",
      "group": "A"
    },
    {
      "code": "CAN",
      "name": "Canada",
      "group": "B"
    },
    {
      "code": "BIH",
      "name": "Bosnia and Herzegovina",
      "group": "B"
    },
    {
      "code": "QAT",
      "name": "Qatar",
      "group": "B"
    },
    {
      "code": "SUI",
      "name": "Switzerland",
      "group": "B"
    },
    {
      "code": "HAI",
      "name": "Haiti",
      "group": "C"
    },
    {
      "code": "SCO",
      "name": "Scotland",
      "group": "C"
    },
    {
      "code": "BRA",
      "name": "Brazil",
      "group": "C"
    },
    {
      "code": "MAR",
      "name": "Morocco",
      "group": "C"
    },
    {
      "code": "USA",
      "name": "United States",
      "group": "D"
    },
    {
      "code": "PAR",
      "name": "Paraguay",
      "group": "D"
    },
    {
      "code": "AUS",
      "name": "Australia",
      "group": "D"
    },
    {
      "code": "TUR",
      "name": "Turkiye",
      "group": "D"
    },
    {
      "code": "CIV",
      "name": "Cote d'Ivoire",
      "group": "E"
    },
    {
      "code": "ECU",
      "name": "Ecuador",
      "group": "E"
    },
    {
      "code": "GER",
      "name": "Germany",
      "group": "E"
    },
    {
      "code": "CUW",
      "name": "Curacao",
      "group": "E"
    },
    {
      "code": "NED",
      "name": "Netherlands",
      "group": "F"
    },
    {
      "code": "JPN",
      "name": "Japan",
      "group": "F"
    },
    {
      "code": "SWE",
      "name": "Sweden",
      "group": "F"
    },
    {
      "code": "TUN",
      "name": "Tunisia",
      "group": "F"
    },
    {
      "code": "IRN",
      "name": "Iran",
      "group": "G"
    },
    {
      "code": "NZL",
      "name": "New Zealand",
      "group": "G"
    },
    {
      "code": "BEL",
      "name": "Belgium",
      "group": "G"
    },
    {
      "code": "EGY",
      "name": "Egypt",
      "group": "G"
    },
    {
      "code": "KSA",
      "name": "Saudi Arabia",
      "group": "H"
    },
    {
      "code": "URU",
      "name": "Uruguay",
      "group": "H"
    },
    {
      "code": "ESP",
      "name": "Spain",
      "group": "H"
    },
    {
      "code": "CPV",
      "name": "Cabo Verde",
      "group": "H"
    },
    {
      "code": "FRA",
      "name": "France",
      "group": "I"
    },
    {
      "code": "SEN",
      "name": "Senegal",
      "group": "I"
    },
    {
      "code": "IRQ",
      "name": "Iraq",
      "group": "I"
    },
    {
      "code": "NOR",
      "name": "Norway",
      "group": "I"
    },
    {
      "code": "ARG",
      "name": "Argentina",
      "group": "J"
    },
    {
      "code": "ALG",
      "name": "Algeria",
      "group": "J"
    },
    {
      "code": "AUT",
      "name": "Austria",
      "group": "J"
    },
    {
      "code": "JOR",
      "name": "Jordan",
      "group": "J"
    },
    {
      "code": "POR",
      "name": "Portugal",
      "group": "K"
    },
    {
      "code": "COD",
      "name": "Congo DR",
      "group": "K"
    },
    {
      "code": "UZB",
      "name": "Uzbekistan",
      "group": "K"
    },
    {
      "code": "COL",
      "name": "Colombia",
      "group": "K"
    },
    {
      "code": "GHA",
      "name": "Ghana",
      "group": "L"
    },
    {
      "code": "PAN",
      "name": "Panama",
      "group": "L"
    },
    {
      "code": "ENG",
      "name": "England",
      "group": "L"
    },
    {
      "code": "CRO",
      "name": "Croatia",
      "group": "L"
    }
  ],
  "matches": [
    {
      "id": "wc2026-a-1",
      "round": "group",
      "group": "A",
      "home": "MEX",
      "away": "RSA",
      "kickoff": "2026-06-11T19:00:00Z"
    },
    {
      "id": "wc2026-a-2",
      "round": "group",
      "group": "A",
      "home": "KOR",
      "away": "CZE",
      "kickoff": "2026-06-12T02:00:00Z"
    },
    {
      "id": "wc2026-a-3",
      "round": "group",
      "group": "A",
      "home": "CZE",
      "away": "RSA",
      "kickoff": "2026-06-18T16:00:00Z"
    },
    {
      "id": "wc2026-a-4",
      "round": "group",
      "group": "A",
      "home": "MEX",
      "away": "KOR",
      "kickoff": "2026-06-19T01:00:00Z"
    },
    {
      "id": "wc2026-a-5",
      "round": "group",
      "group": "A",
      "home": "CZE",
      "away": "MEX",
      "kickoff": "2026-06-25T01:00:00Z"
    },
    {
      "id": "wc2026-a-6",
      "round": "group",
      "group": "A",
      "home": "RSA",
      "away": "KOR",
      "kickoff": "2026-06-25T01:00:00Z"
    },
    {
      "id": "wc2026-b-1",
      "round": "group",
      "group": "B",
      "home": "CAN",
      "away": "BIH",
      "kickoff": "2026-06-12T19:00:00Z"
    },
    {
      "id": "wc2026-b-2",
      "round": "group",
      "group": "B",
      "home": "QAT",
      "away": "SUI",
      "kickoff": "2026-06-13T19:00:00Z"
    },
    {
      "id": "wc2026-b-3",
      "round": "group",
      "group": "B",
      "home": "SUI",
      "away": "BIH",
      "kickoff": "2026-06-18T19:00:00Z"
    },
    {
      "id": "wc2026-b-4",
      "round": "group",
      "group": "B",
      "home": "CAN",
      "away": "QAT",
      "kickoff": "2026-06-18T22:00:00Z"
    },
    {
      "id": "wc2026-b-5",
      "round": "group",
      "group": "B",
      "home": "SUI",
      "away": "CAN",
      "kickoff": "2026-06-24T19:00:00Z"
    },
    {
      "id": "wc2026-b-6",
      "round": "group",
      "group": "B",
      "home": "BIH",
      "away": "QAT",
      "kickoff": "2026-06-24T19:00:00Z"
    },
    {
      "id": "wc2026-c-1",
      "round": "group",
      "group": "C",
      "home": "HAI",
      "away": "SCO",
      "kickoff": "2026-06-14T01:00:00Z"
    },
    {
      "id": "wc2026-c-2",
      "round": "group",
      "group": "C",
      "home": "BRA",
      "away": "MAR",
      "kickoff": "2026-06-13T22:00:00Z"
    },
    {
      "id": "wc2026-c-3",
      "round": "group",
      "group": "C",
      "home": "BRA",
      "away": "HAI",
      "kickoff": "2026-06-20T00:30:00Z"
    },
    {
      "id": "wc2026-c-4",
      "round": "group",
      "group": "C",
      "home": "SCO",
      "away": "MAR",
      "kickoff": "2026-06-19T22:00:00Z"
    },
    {
      "id": "wc2026-c-5",
      "round": "group",
      "group": "C",
      "home": "SCO",
      "away": "BRA",
      "kickoff": "2026-06-24T22:00:00Z"
    },
    {
      "id": "wc2026-c-6",
      "round": "group",
      "group": "C",
      "home": "MAR",
      "away": "HAI",
      "kickoff": "2026-06-24T22:00:00Z"
    },
    {
      "id": "wc2026-d-1",
      "round": "group",
      "group": "D",
      "home": "USA",
      "away": "PAR",
      "kickoff": "2026-06-13T01:00:00Z"
    },
    {
      "id": "wc2026-d-2",
      "round": "group",
      "group": "D",
      "home": "AUS",
      "away": "TUR",
      "kickoff": "2026-06-14T04:00:00Z"
    },
    {
      "id": "wc2026-d-3",
      "round": "group",
      "group": "D",
      "home": "TUR",
      "away": "PAR",
      "kickoff": "2026-06-20T03:00:00Z"
    },
    {
      "id": "wc2026-d-4",
      "round": "group",
      "group": "D",
      "home": "USA",
      "away": "AUS",
      "kickoff": "2026-06-19T19:00:00Z"
    },
    {
      "id": "wc2026-d-5",
      "round": "group",
      "group": "D",
      "home": "TUR",
      "away": "USA",
      "kickoff": "2026-06-26T02:00:00Z"
    },
    {
      "id": "wc2026-d-6",
      "round": "group",
      "group": "D",
      "home": "PAR",
      "away": "AUS",
      "kickoff": "2026-06-26T02:00:00Z"
    },
    {
      "id": "wc2026-e-1",
      "round": "group",
      "group": "E",
      "home": "CIV",
      "away": "ECU",
      "kickoff": "2026-06-14T23:00:00Z"
    },
    {
      "id": "wc2026-e-2",
      "round": "group",
      "group": "E",
      "home": "GER",
      "away": "CUW",
      "kickoff": "2026-06-14T17:00:00Z"
    },
    {
      "id": "wc2026-e-3",
      "round": "group",
      "group": "E",
      "home": "GER",
      "away": "CIV",
      "kickoff": "2026-06-20T20:00:00Z"
    },
    {
      "id": "wc2026-e-4",
      "round": "group",
      "group": "E",
      "home": "ECU",
      "away": "CUW",
      "kickoff": "2026-06-21T00:00:00Z"
    },
    {
      "id": "wc2026-e-5",
      "round": "group",
      "group": "E",
      "home": "CUW",
      "away": "CIV",
      "kickoff": "2026-06-25T20:00:00Z"
    },
    {
      "id": "wc2026-e-6",
      "round": "group",
      "group": "E",
      "home": "ECU",
      "away": "GER",
      "kickoff": "2026-06-25T20:00:00Z"
    },
    {
      "id": "wc2026-f-1",
      "round": "group",
      "group": "F",
      "home": "NED",
      "away": "JPN",
      "kickoff": "2026-06-14T20:00:00Z"
    },
    {
      "id": "wc2026-f-2",
      "round": "group",
      "group": "F",
      "home": "SWE",
      "away": "TUN",
      "kickoff": "2026-06-15T02:00:00Z"
    },
    {
      "id": "wc2026-f-3",
      "round": "group",
      "group": "F",
      "home": "NED",
      "away": "SWE",
      "kickoff": "2026-06-20T17:00:00Z"
    },
    {
      "id": "wc2026-f-4",
      "round": "group",
      "group": "F",
      "home": "TUN",
      "away": "JPN",
      "kickoff": "2026-06-21T04:00:00Z"
    },
    {
      "id": "wc2026-f-5",
      "round": "group",
      "group": "F",
      "home": "JPN",
      "away": "SWE",
      "kickoff": "2026-06-25T23:00:00Z"
    },
    {
      "id": "wc2026-f-6",
      "round": "group",
      "group": "F",
      "home": "TUN",
      "away": "NED",
      "kickoff": "2026-06-25T23:00:00Z"
    },
    {
      "id": "wc2026-g-1",
      "round": "group",
      "group": "G",
      "home": "IRN",
      "away": "NZL",
      "kickoff": "2026-06-16T01:00:00Z"
    },
    {
      "id": "wc2026-g-2",
      "round": "group",
      "group": "G",
      "home": "BEL",
      "away": "EGY",
      "kickoff": "2026-06-15T19:00:00Z"
    },
    {
      "id": "wc2026-g-3",
      "round": "group",
      "group": "G",
      "home": "BEL",
      "away": "IRN",
      "kickoff": "2026-06-21T19:00:00Z"
    },
    {
      "id": "wc2026-g-4",
      "round": "group",
      "group": "G",
      "home": "NZL",
      "away": "EGY",
      "kickoff": "2026-06-22T01:00:00Z"
    },
    {
      "id": "wc2026-g-5",
      "round": "group",
      "group": "G",
      "home": "EGY",
      "away": "IRN",
      "kickoff": "2026-06-27T03:00:00Z"
    },
    {
      "id": "wc2026-g-6",
      "round": "group",
      "group": "G",
      "home": "NZL",
      "away": "BEL",
      "kickoff": "2026-06-27T03:00:00Z"
    },
    {
      "id": "wc2026-h-1",
      "round": "group",
      "group": "H",
      "home": "KSA",
      "away": "URU",
      "kickoff": "2026-06-15T22:00:00Z"
    },
    {
      "id": "wc2026-h-2",
      "round": "group",
      "group": "H",
      "home": "ESP",
      "away": "CPV",
      "kickoff": "2026-06-15T16:00:00Z"
    },
    {
      "id": "wc2026-h-3",
      "round": "group",
      "group": "H",
      "home": "URU",
      "away": "CPV",
      "kickoff": "2026-06-21T22:00:00Z"
    },
    {
      "id": "wc2026-h-4",
      "round": "group",
      "group": "H",
      "home": "ESP",
      "away": "KSA",
      "kickoff": "2026-06-21T16:00:00Z"
    },
    {
      "id": "wc2026-h-5",
      "round": "group",
      "group": "H",
      "home": "CPV",
      "away": "KSA",
      "kickoff": "2026-06-27T00:00:00Z"
    },
    {
      "id": "wc2026-h-6",
      "round": "group",
      "group": "H",
      "home": "URU",
      "away": "ESP",
      "kickoff": "2026-06-27T00:00:00Z"
    },
    {
      "id": "wc2026-i-1",
      "round": "group",
      "group": "I",
      "home": "FRA",
      "away": "SEN",
      "kickoff": "2026-06-16T19:00:00Z"
    },
    {
      "id": "wc2026-i-2",
      "round": "group",
      "group": "I",
      "home": "IRQ",
      "away": "NOR",
      "kickoff": "2026-06-16T22:00:00Z"
    },
    {
      "id": "wc2026-i-3",
      "round": "group",
      "group": "I",
      "home": "NOR",
      "away": "SEN",
      "kickoff": "2026-06-23T00:00:00Z"
    },
    {
      "id": "wc2026-i-4",
      "round": "group",
      "group": "I",
      "home": "FRA",
      "away": "IRQ",
      "kickoff": "2026-06-22T21:00:00Z"
    },
    {
      "id": "wc2026-i-5",
      "round": "group",
      "group": "I",
      "home": "NOR",
      "away": "FRA",
      "kickoff": "2026-06-26T19:00:00Z"
    },
    {
      "id": "wc2026-i-6",
      "round": "group",
      "group": "I",
      "home": "SEN",
      "away": "IRQ",
      "kickoff": "2026-06-26T19:00:00Z"
    },
    {
      "id": "wc2026-j-1",
      "round": "group",
      "group": "J",
      "home": "ARG",
      "away": "ALG",
      "kickoff": "2026-06-17T01:00:00Z"
    },
    {
      "id": "wc2026-j-2",
      "round": "group",
      "group": "J",
      "home": "AUT",
      "away": "JOR",
      "kickoff": "2026-06-17T04:00:00Z"
    },
    {
      "id": "wc2026-j-3",
      "round": "group",
      "group": "J",
      "home": "ARG",
      "away": "AUT",
      "kickoff": "2026-06-22T17:00:00Z"
    },
    {
      "id": "wc2026-j-4",
      "round": "group",
      "group": "J",
      "home": "JOR",
      "away": "ALG",
      "kickoff": "2026-06-23T03:00:00Z"
    },
    {
      "id": "wc2026-j-5",
      "round": "group",
      "group": "J",
      "home": "ALG",
      "away": "AUT",
      "kickoff": "2026-06-28T02:00:00Z"
    },
    {
      "id": "wc2026-j-6",
      "round": "group",
      "group": "J",
      "home": "JOR",
      "away": "ARG",
      "kickoff": "2026-06-28T02:00:00Z"
    },
    {
      "id": "wc2026-k-1",
      "round": "group",
      "group": "K",
      "home": "POR",
      "away": "COD",
      "kickoff": "2026-06-17T17:00:00Z"
    },
    {
      "id": "wc2026-k-2",
      "round": "group",
      "group": "K",
      "home": "UZB",
      "away": "COL",
      "kickoff": "2026-06-18T02:00:00Z"
    },
    {
      "id": "wc2026-k-3",
      "round": "group",
      "group": "K",
      "home": "POR",
      "away": "UZB",
      "kickoff": "2026-06-23T17:00:00Z"
    },
    {
      "id": "wc2026-k-4",
      "round": "group",
      "group": "K",
      "home": "COL",
      "away": "COD",
      "kickoff": "2026-06-24T02:00:00Z"
    },
    {
      "id": "wc2026-k-5",
      "round": "group",
      "group": "K",
      "home": "COL",
      "away": "POR",
      "kickoff": "2026-06-27T23:30:00Z"
    },
    {
      "id": "wc2026-k-6",
      "round": "group",
      "group": "K",
      "home": "COD",
      "away": "UZB",
      "kickoff": "2026-06-27T23:30:00Z"
    },
    {
      "id": "wc2026-l-1",
      "round": "group",
      "group": "L",
      "home": "GHA",
      "away": "PAN",
      "kickoff": "2026-06-17T23:00:00Z"
    },
    {
      "id": "wc2026-l-2",
      "round": "group",
      "group": "L",
      "home": "ENG",
      "away": "CRO",
      "kickoff": "2026-06-17T20:00:00Z"
    },
    {
      "id": "wc2026-l-3",
      "round": "group",
      "group": "L",
      "home": "ENG",
      "away": "GHA",
      "kickoff": "2026-06-23T20:00:00Z"
    },
    {
      "id": "wc2026-l-4",
      "round": "group",
      "group": "L",
      "home": "PAN",
      "away": "CRO",
      "kickoff": "2026-06-23T23:00:00Z"
    },
    {
      "id": "wc2026-l-5",
      "round": "group",
      "group": "L",
      "home": "PAN",
      "away": "ENG",
      "kickoff": "2026-06-27T21:00:00Z"
    },
    {
      "id": "wc2026-l-6",
      "round": "group",
      "group": "L",
      "home": "CRO",
      "away": "GHA",
      "kickoff": "2026-06-27T21:00:00Z"
    },
    {
      "id": "wc2026-r32-1",
      "round": "round_of_32",
      "home": {
        "slot": "2A"
      },
      "away": {
        "slot": "2B"
      },
      "kickoff": "2026-06-28T19:00:00Z"
    },
    {
      "id": "wc2026-r32-2",
      "round": "round_of_32",
      "home": {
        "slot": "1F"
      },
      "away": {
        "slot": "2C"
      },
      "kickoff": "2026-06-30T01:00:00Z"
    },
    {
      "id": "wc2026-r32-3",
      "round": "round_of_32",
      "home": {
        "slot": "1C"
      },
      "away": {
        "slot": "2F"
      },
      "kickoff": "2026-06-29T17:00:00Z"
    },
    {
      "id": "wc2026-r32-4",
      "round": "round_of_32",
      "home": {
        "slot": "2E"
      },
      "away": {
        "slot": "2I"
      },
      "kickoff": "2026-06-30T17:00:00Z"
    },
    {
      "id": "wc2026-r32-5",
      "round": "round_of_32",
      "home": {
        "slot": "1A"
      },
      "away": {
        "slot": "3CEFHI"
      },
      "kickoff": "2026-07-01T01:00:00Z"
    },
    {
      "id": "wc2026-r32-6",
      "round": "round_of_32",
      "home": {
        "slot": "1L"
      },
      "away": {
        "slot": "3EHIJK"
      },
      "kickoff": "2026-07-01T16:00:00Z"
    },
    {
      "id": "wc2026-r32-7",
      "round": "round_of_32",
      "home": {
        "slot": "1D"
      },
      "away": {
        "slot": "3BEFIJ"
      },
      "kickoff": "2026-07-02T00:00:00Z"
    },
    {
      "id": "wc2026-r32-8",
      "round": "round_of_32",
      "home": {
        "slot": "1G"
      },
      "away": {
        "slot": "3AEHIJ"
      },
      "kickoff": "2026-07-01T20:00:00Z"
    },
    {
      "id": "wc2026-r32-9",
      "round": "round_of_32",
      "home": {
        "slot": "2K"
      },
      "away": {
        "slot": "2L"
      },
      "kickoff": "2026-07-02T23:00:00Z"
    },
    {
      "id": "wc2026-r32-10",
      "round": "round_of_32",
      "home": {
        "slot": "1H"
      },
      "away": {
        "slot": "2J"
      },
      "kickoff": "2026-07-02T19:00:00Z"
    },
    {
      "id": "wc2026-r32-11",
      "round": "round_of_32",
      "home": {
        "slot": "1J"
      },
      "away": {
        "slot": "2H"
      },
      "kickoff": "2026-07-03T22:00:00Z"
    },
    {
      "id": "wc2026-r32-12",
      "round": "round_of_32",
      "home": {
        "slot": "2D"
      },
      "away": {
        "slot": "2G"
      },
      "kickoff": "2026-07-03T18:00:00Z"
    },
    {
      "id": "wc2026-r32-13",
      "round": "round_of_32",
      "home": {
        "slot": "1B"
      },
      "away": {
        "slot": "3EFGIJ"
      },
      "kickoff": "2026-07-03T03:00:00Z"
    },
    {
      "id": "wc2026-r32-14",
      "round": "round_of_32",
      "home": {
        "slot": "1K"
      },
      "away": {
        "slot": "3DEIJL"
      },
      "kickoff": "2026-07-04T01:30:00Z"
    },
    {
      "id": "wc2026-r32-15",
      "round": "round_of_32",
      "home": {
        "slot": "1E"
      },
      "away": {
        "slot": "3ABCDF"
      },
      "kickoff": "2026-06-29T20:30:00Z"
    },
    {
      "id": "wc2026-r32-16",
      "round": "round_of_32",
      "home": {
        "slot": "1I"
      },
      "away": {
        "slot": "3CDFGH"
      },
      "kickoff": "2026-06-30T21:00:00Z"
    },
    {
      "id": "wc2026-r16-1",
      "round": "round_of_16",
      "home": {
        "slot": "W R32-1"
      },
      "away": {
        "slot": "W R32-2"
      },
      "kickoff": "2026-07-04T17:00:00Z"
    },
    {
      "id": "wc2026-r16-2",
      "round": "round_of_16",
      "home": {
        "slot": "W R32-3"
      },
      "away": {
        "slot": "W R32-4"
      },
      "kickoff": "2026-07-05T20:00:00Z"
    },
    {
      "id": "wc2026-r16-3",
      "round": "round_of_16",
      "home": {
        "slot": "W R32-5"
      },
      "away": {
        "slot": "W R32-6"
      },
      "kickoff": "2026-07-06T00:00:00Z"
    },
    {
      "id": "wc2026-r16-4",
      "round": "round_of_16",
      "home": {
        "slot": "W R32-7"
      },
      "away": {
        "slot": "W R32-8"
      },
      "kickoff": "2026-07-07T00:00:00Z"
    },
    {
      "id": "wc2026-r16-5",
      "round": "round_of_16",
      "home": {
        "slot": "W R32-9"
      },
      "away": {
        "slot": "W R32-10"
      },
      "kickoff": "2026-07-06T19:00:00Z"
    },
    {
      "id": "wc2026-r16-6",
      "round": "round_of_16",
      "home": {
        "slot": "W R32-11"
      },
      "away": {
        "slot": "W R32-12"
      },
      "kickoff": "2026-07-07T16:00:00Z"
    },
    {
      "id": "wc2026-r16-7",
      "round": "round_of_16",
      "home": {
        "slot": "W R32-13"
      },
      "away": {
        "slot": "W R32-14"
      },
      "kickoff": "2026-07-07T20:00:00Z"
    },
    {
      "id": "wc2026-r16-8",
      "round": "round_of_16",
      "home": {
        "slot": "W R32-15"
      },
      "away": {
        "slot": "W R32-16"
      },
      "kickoff": "2026-07-04T21:00:00Z"
    },
    {
      "id": "wc2026-qf-1",
      "round": "quarter_final",
      "home": {
        "slot": "W R16-1"
      },
      "away": {
        "slot": "W R16-2"
      },
      "kickoff": "2026-07-11T21:00:00Z"
    },
    {
      "id": "wc2026-qf-2",
      "round": "quarter_final",
      "home": {
        "slot": "W R16-3"
      },
      "away": {
        "slot": "W R16-4"
      },
      "kickoff": "2026-07-12T01:00:00Z"
    },
    {
      "id": "wc2026-qf-3",
      "round": "quarter_final",
      "home": {
        "slot": "W R16-5"
      },
      "away": {
        "slot": "W R16-6"
      },
      "kickoff": "2026-07-10T19:00:00Z"
    },
    {
      "id": "wc2026-qf-4",
      "round": "quarter_final",
      "home": {
        "slot": "W R16-7"
      },
      "away": {
        "slot": "W R16-8"
      },
      "kickoff": "2026-07-09T20:00:00Z"
    },
    {
      "id": "wc2026-sf-1",
      "round": "semi_final",
      "home": {
        "slot": "W QF-1"
      },
      "away": {
        "slot": "W QF-2"
      },
      "kickoff": "2026-07-15T19:00:00Z"
    },
    {
      "id": "wc2026-sf-2",
      "round": "semi_final",
      "home": {
        "slot": "W QF-3"
      },
      "away": {
        "slot": "W QF-4"
      },
      "kickoff": "2026-07-14T19:00:00Z"
    },
    {
      "id": "wc2026-third",
      "round": "third_place",
      "home": {
        "slot": "L SF-1"
      },
      "away": {
        "slot": "L SF-2"
      },
      "kickoff": "2026-07-18T21:00:00Z"
    },
    {
      "id": "wc2026-final",
      "round": "final",
      "home": {
        "slot": "W SF-1"
      },
      "away": {
        "slot": "W SF-2"
      },
      "kickoff": "2026-07-19T19:00:00Z"
    }
  ]
}
